broutils/__init__.py
broutils/broutils.py
broutils/file_utils.py
broutils-0.1.1.dist-info/DESCRIPTION.rst
broutils-0.1.1.dist-info/METADATA
broutils-0.1.1.dist-info/RECORD
broutils-0.1.1.dist-info/WHEEL
broutils-0.1.1.dist-info/metadata.json
broutils-0.1.1.dist-info/top_level.txt
