Metadata-Version: 2.0
Name: broutils
Version: 0.1.1
Summary: Bro IDS Python Utilities
Home-page: https://github.com/kitware/broutils
Author: Brian Wylie
Author-email: brian.wylie@kitware.com
License: Apache
Keywords: broutils
Platform: UNKNOWN
Classifier: Development Status :: 2 - Pre-Alpha
Classifier: Intended Audience :: Developers
Classifier: License :: OSI Approved :: Apache Software License
Classifier: Natural Language :: English
Classifier: Programming Language :: Python :: 2.7
Classifier: Programming Language :: Python :: 3.5
Classifier: Programming Language :: Python :: 3.6
Classifier: Programming Language :: Python :: Implementation :: CPython
Classifier: Programming Language :: Python :: Implementation :: PyPy
